statschat/__init__.py
statschat/stats_chat.py
statschat/version.py
statschat/core/__init__.py
statschat/core/code.py
statschat/core/response.py
statschat/core/timeout.py
statschat/drive/ChatGPT.py
statschat/drive/TongYi.py
statschat/drive/WenXinYiYan.py
statschat/drive/__init__.py
statschat/drive/interface.py
statschat/schemes/__init__.py
statschat/schemes/model.py
statschat/schemes/request.py
statschat/schemes/response.py
statschat/utils/__init__.py
statschat/utils/excel.py
statschat/utils/message.py
statschat/utils/tools.py
statschat-0.0.7.dist-info/LICENSE
statschat-0.0.7.dist-info/METADATA
statschat-0.0.7.dist-info/WHEEL
statschat-0.0.7.dist-info/top_level.txt
statschat-0.0.7.dist-info/RECORD
